concat_everywhere/concat.py
concat_everywhere-0.0.1.dist-info/METADATA
concat_everywhere-0.0.1.dist-info/WHEEL
concat_everywhere-0.0.1.dist-info/RECORD
